{
  "@microsoft/fetch-event-source": "obj-6479e1d7",
  "@neondatabase/serverless": "obj-c2c5286a",
  "@playwright/test": "obj-9e909c80",
  "@tanstack/react-query": "obj-4d2d48ab",
  "backend/api/dependencies.py": "obj-79142a15",
  "backend/api/v1/affiliate.py": "obj-6dcedbea",
  "backend/api/v1/agent.py": "obj-49db8d43",
  "backend/api/v1/alerts.py": "obj-7e13f649",
  "backend/api/v1/auth.py": "obj-fc573f11",
  "backend/api/v1/beta.py": "obj-443264b6",
  "backend/api/v1/billing.py": "obj-82da0e51",
  "backend/api/v1/cca.py": "obj-4753ba31",
  "backend/api/v1/community.py": "obj-8f8b798d",
  "backend/api/v1/community_solar.py": "obj-3cbfd6e7",
  "backend/api/v1/compliance.py": "obj-8e3f5411",
  "backend/api/v1/connections/analytics.py": "obj-a2719d29",
  "backend/api/v1/connections/bill_upload.py": "obj-450546a2",
  "backend/api/v1/connections/common.py": "obj-646b9b2b",
  "backend/api/v1/connections/crud.py": "obj-76c7390b",
  "backend/api/v1/connections/direct_sync.py": "obj-abfb69fe",
  "backend/api/v1/connections/email_oauth.py": "obj-a3f0ebb2",
  "backend/api/v1/connections/portal_scrape.py": "obj-43d002c9",
  "backend/api/v1/connections/rates.py": "obj-0bdfd114",
  "backend/api/v1/connections/router.py": "obj-066ea488",
  "backend/api/v1/export.py": "obj-c3d95c8f",
  "backend/api/v1/feedback.py": "obj-4ecc0722",
  "backend/api/v1/forecast.py": "obj-6acd8806",
  "backend/api/v1/gas_rates.py": "obj-4820c493",
  "backend/api/v1/health.py": "obj-675b8584",
  "backend/api/v1/heating_oil.py": "obj-c2c534c8",
  "backend/api/v1/internal/alerts.py": "obj-9c866e22",
  "backend/api/v1/internal/billing.py": "obj-6f20b4e7",
  "backend/api/v1/internal/data_pipeline.py": "obj-a82f1f08",
  "backend/api/v1/internal/data_quality.py": "obj-daee49fe",
  "backend/api/v1/internal/email_scan.py": "obj-047ab3c0",
  "backend/api/v1/internal/ml.py": "obj-801ae636",
  "backend/api/v1/internal/operations.py": "obj-07ed19b3",
  "backend/api/v1/internal/portal_scan.py": "obj-1521b182",
  "backend/api/v1/internal/sync.py": "obj-2cb31851",
  "backend/api/v1/neighborhood.py": "obj-52ff9d74",
  "backend/api/v1/notifications.py": "obj-d5afca18",
  "backend/api/v1/prices.py": "obj-fedf427d",
  "backend/api/v1/prices_analytics.py": "obj-be0ad8c7",
  "backend/api/v1/prices_sse.py": "obj-52e4783e",
  "backend/api/v1/propane.py": "obj-9c251e25",
  "backend/api/v1/public_rates.py": "obj-558c89f7",
  "backend/api/v1/rate_changes.py": "obj-f380ca12",
  "backend/api/v1/recommendations.py": "obj-d781f1a9",
  "backend/api/v1/referrals.py": "obj-e71776a3",
  "backend/api/v1/regulations.py": "obj-be5e680d",
  "backend/api/v1/reports.py": "obj-6561667c",
  "backend/api/v1/savings.py": "obj-2889ff6c",
  "backend/api/v1/suppliers.py": "obj-5d8feac3",
  "backend/api/v1/user.py": "obj-0cb12648",
  "backend/api/v1/user_supplier.py": "obj-593ee849",
  "backend/api/v1/users.py": "obj-fd36663e",
  "backend/api/v1/utility_accounts.py": "obj-af76d613",
  "backend/api/v1/utility_discovery.py": "obj-8ed427ba",
  "backend/api/v1/water.py": "obj-2e999bd6",
  "backend/api/v1/webhooks.py": "obj-801fcb51",
  "backend/app_factory.py": "obj-30d9b366",
  "backend/auth/neon_auth.py": "obj-58fcad61",
  "backend/auth/password.py": "obj-d050d351",
  "backend/compliance/gdpr.py": "obj-79a47676",
  "backend/compliance/repositories.py": "obj-2d9951de",
  "backend/config/database.py": "obj-a807d3bb",
  "backend/config/secrets.py": "obj-5ece13e8",
  "backend/config/settings.py": "obj-83f70b48",
  "backend/gunicorn_config.py": "obj-3bcb4199",
  "backend/integrations/pricing_apis/base.py": "obj-3c095bbf",
  "backend/integrations/pricing_apis/cache.py": "obj-30ea06aa",
  "backend/integrations/pricing_apis/eia.py": "obj-23a7f8ea",
  "backend/integrations/pricing_apis/flatpeak.py": "obj-0d4d0f26",
  "backend/integrations/pricing_apis/iea.py": "obj-a267d976",
  "backend/integrations/pricing_apis/nrel.py": "obj-5d370b96",
  "backend/integrations/pricing_apis/rate_limiter.py": "obj-3c9592bc",
  "backend/integrations/pricing_apis/service.py": "obj-81f4a5ce",
  "backend/integrations/utilityapi.py": "obj-d86f78c1",
  "backend/integrations/weather_service.py": "obj-ea3e4d95",
  "backend/lib/circuit_breaker.py": "obj-37a33fea",
  "backend/lib/tracing.py": "obj-4f972ca3",
  "backend/main.py": "obj-bfadeec7",
  "backend/middleware/rate_limiter.py": "obj-8b04c778",
  "backend/middleware/security_headers.py": "obj-7a39289a",
  "backend/middleware/tracing.py": "obj-0504505f",
  "backend/models/community.py": "obj-317d9bef",
  "backend/models/connections.py": "obj-7cf7cfec",
  "backend/models/consent.py": "obj-91e8571a",
  "backend/models/model_config.py": "obj-4042abee",
  "backend/models/model_version.py": "obj-587bf107",
  "backend/models/notification.py": "obj-f0ca66d9",
  "backend/models/observation.py": "obj-e8b28108",
  "backend/models/price.py": "obj-77ecbd97",
  "backend/models/region.py": "obj-ed93d26f",
  "backend/models/regulation.py": "obj-fe01f5e5",
  "backend/models/supplier.py": "obj-544693cc",
  "backend/models/user.py": "obj-9701c0b6",
  "backend/models/user_supplier.py": "obj-c9b22fa3",
  "backend/models/utility.py": "obj-c2689a98",
  "backend/models/utility_account.py": "obj-022041d1",
  "backend/observability.py": "obj-40d6abb9",
  "backend/repositories/base.py": "obj-c2e83595",
  "backend/repositories/forecast_observation_repository.py": "obj-39f74165",
  "backend/repositories/model_config_repository.py": "obj-7c7454ad",
  "backend/repositories/notification_repository.py": "obj-777c1a33",
  "backend/repositories/price_repository.py": "obj-1a5ec052",
  "backend/repositories/supplier_repository.py": "obj-dbcb5970",
  "backend/repositories/user_repository.py": "obj-a87ac7ea",
  "backend/repositories/utility_account_repository.py": "obj-3c3c8d54",
  "backend/routers/predictions.py": "obj-28e3081f",
  "backend/scripts/backfill_users.py": "obj-f43000d4",
  "backend/scripts/db_maintenance.py": "obj-a723f349",
  "backend/services/ab_test_service.py": "obj-2a186bf6",
  "backend/services/affiliate_service.py": "obj-f91186c4",
  "backend/services/agent_service.py": "obj-e2c22d21",
  "backend/services/alert_renderer.py": "obj-e7e80bd9",
  "backend/services/alert_service.py": "obj-5795848a",
  "backend/services/analytics_service.py": "obj-b167cf0b",
  "backend/services/bill_parser.py": "obj-a0d76d09",
  "backend/services/cca_service.py": "obj-f798ae18",
  "backend/services/community_service.py": "obj-fe42c619",
  "backend/services/community_solar_service.py": "obj-3a2f52c0",
  "backend/services/connection_analytics_service.py": "obj-73294080",
  "backend/services/connection_sync_service.py": "obj-65e035ef",
  "backend/services/data_persistence_helper.py": "obj-fda602e4",
  "backend/services/data_quality_service.py": "obj-6ffccd85",
  "backend/services/dunning_service.py": "obj-30e30b0d",
  "backend/services/email_oauth_service.py": "obj-b7c70854",
  "backend/services/email_scanner_service.py": "obj-52350817",
  "backend/services/email_service.py": "obj-8bb5390a",
  "backend/services/feature_flag_service.py": "obj-d9d012ac",
  "backend/services/forecast_service.py": "obj-d20a3ac3",
  "backend/services/gas_rate_service.py": "obj-e37bf8fe",
  "backend/services/geocoding_service.py": "obj-9c364057",
  "backend/services/heating_oil_service.py": "obj-68a65024",
  "backend/services/hnsw_vector_store.py": "obj-1e5800ce",
  "backend/services/kpi_report_service.py": "obj-e8a2b58c",
  "backend/services/learning_service.py": "obj-fabcb82d",
  "backend/services/maintenance_service.py": "obj-0275f9c0",
  "backend/services/market_intelligence_service.py": "obj-a2e710fc",
  "backend/services/model_version_service.py": "obj-ef040314",
  "backend/services/neighborhood_service.py": "obj-1ac18c7d",
  "backend/services/notification_dispatcher.py": "obj-afb96fde",
  "backend/services/notification_service.py": "obj-f2da3a9b",
  "backend/services/observation_service.py": "obj-b7b16864",
  "backend/services/optimization_report_service.py": "obj-b1a1994e",
  "backend/services/portal_scraper_service.py": "obj-ba58d651",
  "backend/services/price_service.py": "obj-bd5b9859",
  "backend/services/price_sync_service.py": "obj-c001df3a",
  "backend/services/propane_service.py": "obj-db095db3",
  "backend/services/push_notification_service.py": "obj-ae821327",
  "backend/services/rate_change_detector.py": "obj-393442c3",
  "backend/services/rate_export_service.py": "obj-10590962",
  "backend/services/rate_scraper_service.py": "obj-3d2be169",
  "backend/services/recommendation_service.py": "obj-2eba0efa",
  "backend/services/referral_service.py": "obj-1930b2bf",
  "backend/services/savings_aggregator.py": "obj-208e1a6e",
  "backend/services/savings_service.py": "obj-1d66f296",
  "backend/services/stripe_service.py": "obj-78cefdc3",
  "backend/services/utility_discovery_service.py": "obj-a50d278b",
  "backend/services/vector_store.py": "obj-10f8a82b",
  "backend/services/water_rate_service.py": "obj-6ebfac43",
  "backend/services/weather_service.py": "obj-be245c39",
  "backend/utils/encryption.py": "obj-50eaf6b3",
  "better-auth": "obj-f663ce88",
  "clsx": "obj-c2988519",
  "cryptography": "obj-1e226c67",
  "date-fns": "obj-c4ca1e1b",
  "dotenv": "obj-d1d44356",
  "fastapi": "obj-efef2774",
  "frontend/app/(app)/alerts/loading.tsx": "obj-06f5b571",
  "frontend/app/(app)/alerts/page.tsx": "obj-d9aeb3f9",
  "frontend/app/(app)/analytics/page.tsx": "obj-a5e34531",
  "frontend/app/(app)/assistant/loading.tsx": "obj-a07927f9",
  "frontend/app/(app)/assistant/page.tsx": "obj-ad42d651",
  "frontend/app/(app)/auth/callback/page.tsx": "obj-7f7cf720",
  "frontend/app/(app)/auth/forgot-password/page.tsx": "obj-54bea00e",
  "frontend/app/(app)/auth/login/page.tsx": "obj-7e00aae0",
  "frontend/app/(app)/auth/reset-password/page.tsx": "obj-650a0750",
  "frontend/app/(app)/auth/signup/page.tsx": "obj-df764360",
  "frontend/app/(app)/auth/verify-email/page.tsx": "obj-539e130c",
  "frontend/app/(app)/beta-signup/page.tsx": "obj-5a237286",
  "frontend/app/(app)/community-solar/page.tsx": "obj-693d8dc8",
  "frontend/app/(app)/community/loading.tsx": "obj-fca735a2",
  "frontend/app/(app)/community/page.tsx": "obj-2ff365fd",
  "frontend/app/(app)/connections/error.tsx": "obj-ce6af7fd",
  "frontend/app/(app)/connections/loading.tsx": "obj-137fc692",
  "frontend/app/(app)/connections/page.tsx": "obj-8b5313f4",
  "frontend/app/(app)/dashboard/error.tsx": "obj-02a76606",
  "frontend/app/(app)/dashboard/loading.tsx": "obj-d799d7eb",
  "frontend/app/(app)/dashboard/page.tsx": "obj-423b311e",
  "frontend/app/(app)/error.tsx": "obj-a83aa47e",
  "frontend/app/(app)/gas-rates/page.tsx": "obj-19821daf",
  "frontend/app/(app)/heating-oil/page.tsx": "obj-f0cec493",
  "frontend/app/(app)/layout.tsx": "obj-a288e29c",
  "frontend/app/(app)/onboarding/page.tsx": "obj-361d310b",
  "frontend/app/(app)/optimize/error.tsx": "obj-40896322",
  "frontend/app/(app)/optimize/loading.tsx": "obj-2965b7e5",
  "frontend/app/(app)/optimize/page.tsx": "obj-97cecc06",
  "frontend/app/(app)/prices/error.tsx": "obj-6637360f",
  "frontend/app/(app)/prices/loading.tsx": "obj-f5f11e3a",
  "frontend/app/(app)/prices/page.tsx": "obj-563a2267",
  "frontend/app/(app)/propane/page.tsx": "obj-f7fc0eec",
  "frontend/app/(app)/settings/error.tsx": "obj-e26c0de4",
  "frontend/app/(app)/settings/loading.tsx": "obj-0bc10086",
  "frontend/app/(app)/settings/page.tsx": "obj-13289764",
  "frontend/app/(app)/suppliers/error.tsx": "obj-d4f9a5d4",
  "frontend/app/(app)/suppliers/loading.tsx": "obj-8fcfd4c4",
  "frontend/app/(app)/suppliers/page.tsx": "obj-53055bea",
  "frontend/app/(app)/water/page.tsx": "obj-aa0a98a8",
  "frontend/app/(dev)/architecture/page.tsx": "obj-fbd270e3",
  "frontend/app/(dev)/layout.tsx": "obj-8d9fbec2",
  "frontend/app/api/auth/[...all]/route.ts": "obj-e967d16f",
  "frontend/app/api/checkout/route.ts": "obj-3cee0ba1",
  "frontend/app/api/dev/diagrams/[name]/route.ts": "obj-33a95880",
  "frontend/app/api/dev/diagrams/route.ts": "obj-e7554a7b",
  "frontend/app/api/pwa-icon/route.tsx": "obj-d0d77149",
  "frontend/app/apple-icon.tsx": "obj-4f03a886",
  "frontend/app/error.tsx": "obj-414fe42a",
  "frontend/app/global-error.tsx": "obj-b3ee1057",
  "frontend/app/icon.tsx": "obj-664405c8",
  "frontend/app/layout.tsx": "obj-7b8a20a3",
  "frontend/app/manifest.ts": "obj-7c1d6cf3",
  "frontend/app/not-found.tsx": "obj-7568cbd9",
  "frontend/app/page.tsx": "obj-0069f6ec",
  "frontend/app/pricing/page.tsx": "obj-2e879bc6",
  "frontend/app/privacy/page.tsx": "obj-5f0c67db",
  "frontend/app/rates/[state]/[utility]/page.tsx": "obj-964bfff9",
  "frontend/app/robots.ts": "obj-f92464a9",
  "frontend/app/sitemap.ts": "obj-4c0257b3",
  "frontend/app/terms/page.tsx": "obj-b0e5936e",
  "frontend/components/affiliate/FTCDisclosure.tsx": "obj-3655c4dd",
  "frontend/components/agent/AgentChat.tsx": "obj-3b6b2261",
  "frontend/components/alerts/AlertForm.tsx": "obj-f99af289",
  "frontend/components/alerts/AlertsContent.tsx": "obj-35b6be84",
  "frontend/components/analytics/AnalyticsDashboard.tsx": "obj-3e4ef506",
  "frontend/components/analytics/DataExport.tsx": "obj-1b5eb35b",
  "frontend/components/analytics/ForecastWidget.tsx": "obj-e189a4fc",
  "frontend/components/analytics/OptimizationReport.tsx": "obj-e73c74a5",
  "frontend/components/auth/LoginForm.tsx": "obj-ef6244c0",
  "frontend/components/auth/SignupForm.tsx": "obj-77d7a18d",
  "frontend/components/cca/CCAAlert.tsx": "obj-49425533",
  "frontend/components/cca/CCAComparison.tsx": "obj-92b0a48a",
  "frontend/components/cca/CCAInfo.tsx": "obj-d3b85720",
  "frontend/components/charts/ForecastChart.tsx": "obj-d1df02de",
  "frontend/components/charts/PriceLineChart.tsx": "obj-9d3d16e5",
  "frontend/components/charts/SavingsDonut.tsx": "obj-9a482f6f",
  "frontend/components/charts/ScheduleTimeline.tsx": "obj-5aff3792",
  "frontend/components/community-solar/CommunitySolarContent.tsx": "obj-ebc3ae81",
  "frontend/components/community-solar/SavingsCalculator.tsx": "obj-25a49408",
  "frontend/components/community/CommunityStats.tsx": "obj-579100a3",
  "frontend/components/community/PostForm.tsx": "obj-a25e865b",
  "frontend/components/community/PostList.tsx": "obj-7dc908ac",
  "frontend/components/community/ReportButton.tsx": "obj-323b1844",
  "frontend/components/community/VoteButton.tsx": "obj-afe6e043",
  "frontend/components/connections/BillUploadDropZone.tsx": "obj-6e5b2890",
  "frontend/components/connections/BillUploadFilePreview.tsx": "obj-a8ea21fc",
  "frontend/components/connections/BillUploadForm.tsx": "obj-e468252a",
  "frontend/components/connections/BillUploadProgress.tsx": "obj-c8a90a1a",
  "frontend/components/connections/BillUploadResults.tsx": "obj-da0cf698",
  "frontend/components/connections/BillUploadTypes.ts": "obj-56cb2de8",
  "frontend/components/connections/ConnectionAnalytics.tsx": "obj-92bf51ac",
  "frontend/components/connections/ConnectionCard.tsx": "obj-de60fec6",
  "frontend/components/connections/ConnectionMethodPicker.tsx": "obj-053be063",
  "frontend/components/connections/ConnectionRates.tsx": "obj-2b92f88f",
  "frontend/components/connections/ConnectionUploadFlow.tsx": "obj-ca5df6e9",
  "frontend/components/connections/ConnectionsOverview.tsx": "obj-6f1ee81c",
  "frontend/components/connections/DirectLoginForm.tsx": "obj-5f1f0c37",
  "frontend/components/connections/EmailConnectionFlow.tsx": "obj-b7fc48ea",
  "frontend/components/connections/ExtractedField.tsx": "obj-d993f4a3",
  "frontend/components/connections/PortalConnectionFlow.tsx": "obj-337c1e1b",
  "frontend/components/connections/analytics/ConnectionHealthCard.tsx": "obj-66878402",
  "frontend/components/connections/analytics/RateComparisonCard.tsx": "obj-3491db9d",
  "frontend/components/connections/analytics/RateHistoryCard.tsx": "obj-340817a1",
  "frontend/components/connections/analytics/SavingsEstimateCard.tsx": "obj-4ad98f80",
  "frontend/components/connections/analytics/index.ts": "obj-62694b09",
  "frontend/components/connections/analytics/types.ts": "obj-9e0e6608",
  "frontend/components/dashboard/AllUtilitiesTab.tsx": "obj-a9422ba5",
  "frontend/components/dashboard/CombinedSavingsCard.tsx": "obj-5b3fda9c",
  "frontend/components/dashboard/CompletionProgress.tsx": "obj-3f0e7c15",
  "frontend/components/dashboard/DashboardCharts.tsx": "obj-23b51b55",
  "frontend/components/dashboard/DashboardContent.tsx": "obj-6ee6df54",
  "frontend/components/dashboard/DashboardForecast.tsx": "obj-9cb7a2cf",
  "frontend/components/dashboard/DashboardSchedule.tsx": "obj-412334ea",
  "frontend/components/dashboard/DashboardStatsRow.tsx": "obj-ddd65587",
  "frontend/components/dashboard/DashboardTabs.tsx": "obj-483796d2",
  "frontend/components/dashboard/DashboardTypes.ts": "obj-de70aeb6",
  "frontend/components/dashboard/NeighborhoodCard.tsx": "obj-31e1ad08",
  "frontend/components/dashboard/SetupChecklist.tsx": "obj-57fc7d0a",
  "frontend/components/dashboard/UtilityDiscoveryCard.tsx": "obj-f05f4844",
  "frontend/components/dashboard/UtilityTabShell.tsx": "obj-da113da1",
  "frontend/components/dev/DevBanner.tsx": "obj-c2e89e5c",
  "frontend/components/dev/DiagramEditor.tsx": "obj-d81d5d96",
  "frontend/components/dev/DiagramList.tsx": "obj-8bf51bc6",
  "frontend/components/dev/ExcalidrawWrapper.tsx": "obj-01652dbd",
  "frontend/components/error-boundary.tsx": "obj-e127517f",
  "frontend/components/feedback/FeedbackWidget.tsx": "obj-203d9581",
  "frontend/components/gamification/SavingsTracker.tsx": "obj-39ad2bf7",
  "frontend/components/gas/GasRatesContent.tsx": "obj-2be41783",
  "frontend/components/heating-oil/DealerList.tsx": "obj-ff623b31",
  "frontend/components/heating-oil/HeatingOilDashboard.tsx": "obj-b9d190ba",
  "frontend/components/heating-oil/OilPriceHistory.tsx": "obj-13ce3e26",
  "frontend/components/layout/Header.tsx": "obj-7f8e5e39",
  "frontend/components/layout/NotificationBell.tsx": "obj-42587576",
  "frontend/components/layout/Sidebar.tsx": "obj-3593264f",
  "frontend/components/layout/StatusBadge.tsx": "obj-ee25df01",
  "frontend/components/onboarding/AccountLinkStep.tsx": "obj-b36b1694",
  "frontend/components/onboarding/OnboardingWizard.tsx": "obj-0e11f6de",
  "frontend/components/onboarding/RegionSelector.tsx": "obj-25fe48c6",
  "frontend/components/onboarding/SupplierPicker.tsx": "obj-737e90b7",
  "frontend/components/onboarding/UtilityTypeSelector.tsx": "obj-be358bbc",
  "frontend/components/page-error-fallback.tsx": "obj-06eb4c99",
  "frontend/components/prices/PricesContent.tsx": "obj-e9ba1aff",
  "frontend/components/propane/FillUpTiming.tsx": "obj-27db1acc",
  "frontend/components/propane/PropaneDashboard.tsx": "obj-65f79d29",
  "frontend/components/propane/PropanePriceHistory.tsx": "obj-e1a8de61",
  "frontend/components/providers/QueryProvider.tsx": "obj-8b1b2859",
  "frontend/components/pwa/InstallPrompt.tsx": "obj-50bf1930",
  "frontend/components/pwa/ServiceWorkerRegistrar.tsx": "obj-0973ece3",
  "frontend/components/rate-changes/AlertPreferences.tsx": "obj-b70e14bc",
  "frontend/components/rate-changes/RateChangeCard.tsx": "obj-03235734",
  "frontend/components/rate-changes/RateChangeFeed.tsx": "obj-cc4f8d9b",
  "frontend/components/seo/RatePageContent.tsx": "obj-6844a0d1",
  "frontend/components/suppliers/ComparisonTable.tsx": "obj-79fe09d3",
  "frontend/components/suppliers/SetSupplierDialog.tsx": "obj-8c915a79",
  "frontend/components/suppliers/SupplierAccountForm.tsx": "obj-fd9ce530",
  "frontend/components/suppliers/SupplierCard.tsx": "obj-b681c310",
  "frontend/components/suppliers/SupplierSelector.tsx": "obj-f8f04da7",
  "frontend/components/suppliers/SuppliersContent.tsx": "obj-8383048c",
  "frontend/components/suppliers/SwitchWizard.tsx": "obj-14b8735d",
  "frontend/components/ui/badge.tsx": "obj-d620086a",
  "frontend/components/ui/button.tsx": "obj-a1a33246",
  "frontend/components/ui/card.tsx": "obj-77f3d7ec",
  "frontend/components/ui/input.tsx": "obj-f924871f",
  "frontend/components/ui/modal.tsx": "obj-eb8b11b7",
  "frontend/components/ui/skeleton.tsx": "obj-9013779a",
  "frontend/components/ui/toast.tsx": "obj-25d2f6dd",
  "frontend/components/water/ConservationTips.tsx": "obj-29c6df07",
  "frontend/components/water/WaterDashboard.tsx": "obj-6db69110",
  "frontend/components/water/WaterRateBenchmark.tsx": "obj-0fa429bf",
  "frontend/components/water/WaterTierCalculator.tsx": "obj-99c4caa5",
  "frontend/e2e/helpers/auth.ts": "obj-5b74eb34",
  "frontend/lib/analytics/clarity.tsx": "obj-fabe7c8b",
  "frontend/lib/api/affiliate.ts": "obj-728fce5c",
  "frontend/lib/api/agent.ts": "obj-53c136da",
  "frontend/lib/api/alerts.ts": "obj-6b06447a",
  "frontend/lib/api/cca.ts": "obj-942e20fd",
  "frontend/lib/api/circuit-breaker.ts": "obj-5672965a",
  "frontend/lib/api/client.ts": "obj-8c977895",
  "frontend/lib/api/community-solar.ts": "obj-4e1b96c7",
  "frontend/lib/api/community.ts": "obj-8e11b8fa",
  "frontend/lib/api/export.ts": "obj-46282863",
  "frontend/lib/api/forecast.ts": "obj-c95d0ef3",
  "frontend/lib/api/gas-rates.ts": "obj-ed31e5c0",
  "frontend/lib/api/heating-oil.ts": "obj-30c47241",
  "frontend/lib/api/neighborhood.ts": "obj-57ff80b8",
  "frontend/lib/api/notifications.ts": "obj-f42c2c6a",
  "frontend/lib/api/optimization.ts": "obj-33b84111",
  "frontend/lib/api/portal.ts": "obj-cf4d2230",
  "frontend/lib/api/prices.ts": "obj-4f422f29",
  "frontend/lib/api/profile.ts": "obj-40f0303b",
  "frontend/lib/api/propane.ts": "obj-95ed8fbd",
  "frontend/lib/api/rate-changes.ts": "obj-99897c0e",
  "frontend/lib/api/reports.ts": "obj-34247a17",
  "frontend/lib/api/savings.ts": "obj-dd307033",
  "frontend/lib/api/suppliers.ts": "obj-37dd7667",
  "frontend/lib/api/utility-discovery.ts": "obj-de215cb1",
  "frontend/lib/api/water.ts": "obj-312d5ddb",
  "frontend/lib/auth/client.ts": "obj-483b42dc",
  "frontend/lib/auth/server.ts": "obj-75ddb481",
  "frontend/lib/config/env.ts": "obj-f8c65245",
  "frontend/lib/config/seo.ts": "obj-bd39b951",
  "frontend/lib/constants/chartTokens.ts": "obj-8e5e2a56",
  "frontend/lib/constants/regions.ts": "obj-89a463a3",
  "frontend/lib/contexts/sidebar-context.tsx": "obj-a7fdceae",
  "frontend/lib/contexts/toast-context.tsx": "obj-576b8d09",
  "frontend/lib/email/send.ts": "obj-b95be167",
  "frontend/lib/hooks/useAgent.ts": "obj-300028d4",
  "frontend/lib/hooks/useAlerts.ts": "obj-5415725c",
  "frontend/lib/hooks/useAuth.tsx": "obj-3471cfec",
  "frontend/lib/hooks/useCCA.ts": "obj-1a07802c",
  "frontend/lib/hooks/useCombinedSavings.ts": "obj-7c59e8d2",
  "frontend/lib/hooks/useCommunity.ts": "obj-b0208659",
  "frontend/lib/hooks/useCommunitySolar.ts": "obj-c8bbc60d",
  "frontend/lib/hooks/useConnections.ts": "obj-1f108bd4",
  "frontend/lib/hooks/useDiagrams.ts": "obj-f195b075",
  "frontend/lib/hooks/useExport.ts": "obj-97f261a0",
  "frontend/lib/hooks/useForecast.ts": "obj-2596d43e",
  "frontend/lib/hooks/useGasRates.ts": "obj-c23a127b",
  "frontend/lib/hooks/useGeocoding.ts": "obj-5121d089",
  "frontend/lib/hooks/useHeatingOil.ts": "obj-7188286b",
  "frontend/lib/hooks/useNeighborhood.ts": "obj-8aa34665",
  "frontend/lib/hooks/useNotifications.ts": "obj-10c4b44d",
  "frontend/lib/hooks/useOptimization.ts": "obj-7c972902",
  "frontend/lib/hooks/usePrices.ts": "obj-e5382980",
  "frontend/lib/hooks/useProfile.ts": "obj-944220fe",
  "frontend/lib/hooks/usePropane.ts": "obj-fda8b849",
  "frontend/lib/hooks/useRateChanges.ts": "obj-c32d7614",
  "frontend/lib/hooks/useRealtime.ts": "obj-1756762b",
  "frontend/lib/hooks/useReports.ts": "obj-9f30fb49",
  "frontend/lib/hooks/useSavings.ts": "obj-f7a5c508",
  "frontend/lib/hooks/useSuppliers.ts": "obj-5da4e0b0",
  "frontend/lib/hooks/useUtilityDiscovery.ts": "obj-ee029980",
  "frontend/lib/hooks/useWater.ts": "obj-f95700e6",
  "frontend/lib/notifications/onesignal.ts": "obj-d96588ef",
  "frontend/lib/store/settings.ts": "obj-41a6cd01",
  "frontend/lib/utils/calculations.ts": "obj-6e552235",
  "frontend/lib/utils/cn.ts": "obj-b61c828b",
  "frontend/lib/utils/devGate.ts": "obj-611e4b69",
  "frontend/lib/utils/format.ts": "obj-28b9e8bd",
  "frontend/lib/utils/url.ts": "obj-97f22621",
  "frontend/middleware.ts": "obj-0f72cdae",
  "frontend/next-env.d.ts": "obj-1f6577ca",
  "frontend/playwright.config.ts": "obj-6cfafc2b",
  "frontend/tailwind.config.ts": "obj-46ce8d95",
  "frontend/types/api-helpers.ts": "obj-40ecb30f",
  "frontend/types/generated/api.ts": "obj-ecee86e7",
  "frontend/types/index.ts": "obj-2daa29ec",
  "fs": "obj-9599cbfe",
  "google": "obj-14e7fbc7",
  "groq": "obj-472cbe95",
  "hnswlib": "obj-5f410103",
  "httpx": "obj-76e75962",
  "lucide-react": "obj-3b1914ec",
  "ml/data/feature_engineering.py": "obj-7e397ecd",
  "ml/evaluation/backtesting.py": "obj-a0fa1c4d",
  "ml/evaluation/metrics.py": "obj-3b2a8bfd",
  "ml/inference/ensemble_predictor.py": "obj-22c413aa",
  "ml/inference/predictor.py": "obj-10a10cb1",
  "ml/models/ensemble.py": "obj-56cbfc5c",
  "ml/models/price_forecaster.py": "obj-2d1d381a",
  "ml/optimization/appliance_models.py": "obj-a7458c98",
  "ml/optimization/constraints.py": "obj-49070703",
  "ml/optimization/load_shifter.py": "obj-d658fbe5",
  "ml/optimization/objective.py": "obj-df2e1d37",
  "ml/optimization/scheduler.py": "obj-976dd585",
  "ml/optimization/switching_decision.py": "obj-1d4d922f",
  "ml/optimization/visualization.py": "obj-8e07545d",
  "ml/training/cnn_lstm_trainer.py": "obj-2560a93a",
  "ml/training/hyperparameter_tuning.py": "obj-014da415",
  "ml/training/train_forecaster.py": "obj-90a724ef",
  "next": "obj-817ce600",
  "nh3": "obj-24488d9a",
  "nodemailer": "obj-938c0e72",
  "numpy": "obj-56bfc2ae",
  "opentelemetry": "obj-acf6d753",
  "pandas": "obj-f34b347b",
  "path": "obj-d74a3178",
  "pydantic": "obj-ca074f6e",
  "react": "obj-3c5caf59",
  "recharts": "obj-600130bb",
  "redis": "obj-f58238df",
  "resend": "obj-d4d3b508",
  "scipy": "obj-2843da8d",
  "sklearn": "obj-05618e02",
  "sqlalchemy": "obj-9dd7ce50",
  "starlette": "obj-5b5d0db4",
  "stripe": "obj-ccb15426",
  "structlog": "obj-ff3c073d",
  "tailwind-merge": "obj-0ac99da6",
  "tailwindcss": "obj-574c933f",
  "uvicorn": "obj-935c5843",
  "workers/api-gateway/src/config.ts": "obj-c2f1947d",
  "workers/api-gateway/src/handlers/proxy.ts": "obj-b8867473",
  "workers/api-gateway/src/index.ts": "obj-5ac243d8",
  "workers/api-gateway/src/middleware/cache.ts": "obj-b21cc558",
  "workers/api-gateway/src/middleware/cors.ts": "obj-2635a966",
  "workers/api-gateway/src/middleware/internal-auth.ts": "obj-80c08a74",
  "workers/api-gateway/src/middleware/observability.ts": "obj-673dd43c",
  "workers/api-gateway/src/middleware/rate-limiter.ts": "obj-964d91c1",
  "workers/api-gateway/src/middleware/security.ts": "obj-2546ae34",
  "workers/api-gateway/src/router.ts": "obj-49ca9324",
  "workers/api-gateway/src/types.ts": "obj-84547931",
  "zustand": "obj-96955c88"
}
